unit_converter/__init__.py
unit_converter/converter.py
holosen_unit_converter-0.1.0.dist-info/METADATA
holosen_unit_converter-0.1.0.dist-info/WHEEL
holosen_unit_converter-0.1.0.dist-info/top_level.txt
holosen_unit_converter-0.1.0.dist-info/RECORD
