Metadata-Version: 2.1
Name: holosen-unit-converter
Version: 0.1.0
Summary: A simple Python library to convert between different units
Home-page: https://github.com/badrnezhad/unit-converter
Author: Hossein Badrnezhad
Author-email: holosenpythonknight@gmail.com
Classifier: Programming Language :: Python :: 3
Classifier: License :: OSI Approved :: MIT License
Classifier: Operating System :: OS Independent
Requires-Python: >=3.6
